{
    //^VSCodium
    //$VSCodium

    //^Vim
    "vim.insertModeKeyBindings": [
    {
      "before": ["j", "j"],
      "after": ["<Esc>"]
    }
  ],
  "vim.normalModeKeyBindingsNonRecursive": [
    {
      "before": ["<leader>", "d"],
      "after": ["d", "d"]
    },
    {
      "before": ["<C-n>"],
      "commands": [":nohl"]
    },
    {
      "before": ["<leader>", "e"],
      "commands": ["workbench.view.explorer.toggle"]
    },
    {
      "before": ["K"],
      "commands": ["lineBreakInsert"],
      "silent": true
    }
  ]
  //$Vim
}
